animepahe_dlr/__init__.py
animepahe_dlr/ap_dlr.py
animepahe_dlr/gecko_installer.py
animepahe_dlr/driver_extensions/mozilla_cc3@internetdownloadmanager.com.xpi
animepahe_dlr/driver_extensions/uBlock0@raymondhill.net.xpi
animepahe_dlr/driver_extensions/universal-bypass.xpi
animepahe_dlr-0.2.1.dist-info/METADATA
animepahe_dlr-0.2.1.dist-info/WHEEL
animepahe_dlr-0.2.1.dist-info/entry_points.txt
animepahe_dlr-0.2.1.dist-info/license.md
animepahe_dlr-0.2.1.dist-info/top_level.txt
animepahe_dlr-0.2.1.dist-info/RECORD
