Metadata-Version: 2.1
Name: animepahe-dlr
Version: 0.2.1
Summary: A python script to automate downloads from animepahe
Home-page: https://github.com/ed-archer/animepahe-dlr
Author: ed-archer
License: MIT
Platform: UNKNOWN
Classifier: Programming Language :: Python :: 3
Classifier: Programming Language :: Python :: 3.9
Classifier: License :: OSI Approved :: MIT License
Classifier: Operating System :: OS Independent
Classifier: Operating System :: Microsoft :: Windows :: Windows 10
Classifier: Operating System :: POSIX :: Linux
Requires-Dist: beautifulsoup4 (>=4.9.3)
Requires-Dist: selenium (>=3.141.0)
Requires-Dist: requests (>=2.25.1)
Requires-Dist: tqdm (>=4.61.0)
